jupyter_deploy/__init__.py
jupyter_deploy/cmd_utils.py
jupyter_deploy/fs_utils.py
jupyter_deploy/py.typed
jupyter_deploy/str_utils.py
jupyter_deploy/template_utils.py
jupyter_deploy/api/__init__.py
jupyter_deploy/cli/app.py
jupyter_deploy/cli/servers_app.py
jupyter_deploy/cli/variables_decorator.py
jupyter_deploy/engine/__init__.py
jupyter_deploy/engine/engine_config.py
jupyter_deploy/engine/engine_down.py
jupyter_deploy/engine/engine_open.py
jupyter_deploy/engine/engine_up.py
jupyter_deploy/engine/engine_variables.py
jupyter_deploy/engine/enum.py
jupyter_deploy/engine/vardefs.py
jupyter_deploy/engine/terraform/tf_config.py
jupyter_deploy/engine/terraform/tf_constants.py
jupyter_deploy/engine/terraform/tf_down.py
jupyter_deploy/engine/terraform/tf_open.py
jupyter_deploy/engine/terraform/tf_plan.py
jupyter_deploy/engine/terraform/tf_up.py
jupyter_deploy/engine/terraform/tf_vardefs.py
jupyter_deploy/engine/terraform/tf_varfiles.py
jupyter_deploy/engine/terraform/tf_variables.py
jupyter_deploy/engine/terraform/tf_verify.py
jupyter_deploy/handlers/__init__.py
jupyter_deploy/handlers/project/__init__.py
jupyter_deploy/handlers/project/config_handler.py
jupyter_deploy/handlers/project/down_handler.py
jupyter_deploy/handlers/project/init_handler.py
jupyter_deploy/handlers/project/open_handler.py
jupyter_deploy/handlers/project/up_handler.py
jupyter_deploy/handlers/project/variables_handler.py
jupyter_deploy/infrastructure/__init__.py
jupyter_deploy/infrastructure/enum.py
jupyter_deploy/provider/__init__.py
jupyter_deploy/provider/enum.py
jupyter_deploy/provider/aws/__init__.py
jupyter_deploy/provider/aws/aws_cli.py
jupyter_deploy/provider/aws/ssm_plugin.py
jupyter_deploy_test-0.1.0a1.dist-info/METADATA
jupyter_deploy_test-0.1.0a1.dist-info/WHEEL
jupyter_deploy_test-0.1.0a1.dist-info/entry_points.txt
jupyter_deploy_test-0.1.0a1.dist-info/licenses/LICENSE
jupyter_deploy_test-0.1.0a1.dist-info/RECORD
