Metadata-Version: 2.4
Name: jupyter-deploy-test
Version: 0.1.0a1
Summary: CLI based tool to deploy Jupyter application that integrates with infrastructure as code frameworks.
Author-email: Jonathan Guinegagne <jggg@amazon.com>
License-File: LICENSE
Requires-Python: >=3.12
Requires-Dist: click<8.2.0
Requires-Dist: decorator>=5.2.1
Requires-Dist: jupyter-core>=5.0.0
Requires-Dist: jupyter-deploy-tf-aws-ec2-traefik-test
Requires-Dist: packaging>=25.0
Requires-Dist: pydantic>=2.11.5
Requires-Dist: python-hcl2>=7.2.1
Requires-Dist: typer>=0.15.4
Provides-Extra: aws
Requires-Dist: boto3-stubs>=1.38.6; extra == 'aws'
Requires-Dist: boto3>=1.38.6; extra == 'aws'
Requires-Dist: mypy-boto3-ec2>=1.38.6; extra == 'aws'
